wordexpansion/__init__.py
wordexpansion/so_pmi.py
wordexpansion/w2v.py
wordexpansion-1.1.dist-info/LICENSE
wordexpansion-1.1.dist-info/METADATA
wordexpansion-1.1.dist-info/WHEEL
wordexpansion-1.1.dist-info/top_level.txt
wordexpansion-1.1.dist-info/RECORD
