Metadata-Version: 2.1
Name: wordexpansion
Version: 1.1
Summary: UNKNOWN
Home-page: https://github.com/hidadeng/wordexpansion
Author: 大邓
Author-email: thunderhit@qq.com
License: MIT
Keywords: knowledge graph,text analysis,event extraction
Platform: UNKNOWN
Requires-Python: >=3.5
